nssvie/__init__.py
nssvie/_version.py
nssvie/_integral_equations/__init__.py
nssvie/_integral_equations/base.py
nssvie/_integral_equations/svie.py
nssvie/_orthogonal_functions/__init__.py
nssvie/_orthogonal_functions/base.py
nssvie/_orthogonal_functions/bpf.py
nssvie-0.0.4.dist-info/LICENCE
nssvie-0.0.4.dist-info/METADATA
nssvie-0.0.4.dist-info/WHEEL
nssvie-0.0.4.dist-info/top_level.txt
nssvie-0.0.4.dist-info/RECORD
