Metadata-Version: 2.1
Name: nssvie
Version: 0.0.4
Summary: Numerical solution of stochastic Volterra integral equations via a stochastic operational matrix based on block pulse functions.
Home-page: https://github.com/dsagolla/nssvie
Download-URL: https://github.com/dsagolla/nssvie/archive/main.zip
Author: Daniel Sagolla
Author-email: daniel.sagolla@udo.edu
Project-URL: Documentation, https://nssvie.readthedocs.io/en/latest/
Project-URL: Source, https://github.com/dsagolla/nssvie
Project-URL: Tracker, https://github.com/dsagolla/nssvie/issues
Keywords: orthogonal-functions sde stochastic-differential-equations stochastic-volterra-integral-equation numerical-solution block-pulse-functions
Platform: Linux
Platform: OSX
Platform: Windows
Classifier: Programming Language :: Python :: 3.7
Classifier: Programming Language :: Python :: 3.8
Classifier: Programming Language :: Python :: 3.9
Classifier: Programming Language :: Python :: 3.10
Classifier: Programming Language :: Python :: 3.11
Classifier: License :: OSI Approved :: GNU General Public License v3 (GPLv3)
Classifier: Operating System :: OS Independent
Classifier: Natural Language :: English
Classifier: Intended Audience :: Science/Research
Classifier: Intended Audience :: Developers
Classifier: Topic :: Software Development
Classifier: Topic :: Scientific/Engineering
Classifier: Topic :: Scientific/Engineering :: Mathematics
Classifier: Topic :: Software Development :: Libraries :: Python Modules
Requires-Python: >=3.6
License-File: LICENCE
Requires-Dist: stochastic
Requires-Dist: numpy
Requires-Dist: scipy
Provides-Extra: docs
Provides-Extra: test
